MANIFEST.in
README.md
setup.cfg
setup.py
django_params_validator/__init__.py
django_params_validator.egg-info/PKG-INFO
django_params_validator.egg-info/SOURCES.txt
django_params_validator.egg-info/dependency_links.txt
django_params_validator.egg-info/requires.txt
django_params_validator.egg-info/top_level.txt