Metadata-Version: 1.1
Name: django-params-validator
Version: 1.1.6
Summary: Decorator for Django REST Framework for validate params
Home-page: https://github.com/wudizhangzhi/django-params-validator
Author: wudizhangzhi
Author-email: 554330595@qq.com
License: MIT
Keywords: rest,django,api,params,parameters,djangorestframework,decorator
Platform: UNKNOWN
Classifier: Development Status :: 4 - Beta
Classifier: Environment :: Web Environment
Classifier: Framework :: Django
Classifier: Intended Audience :: Developers
Classifier: Intended Audience :: System Administrators
Classifier: Operating System :: OS Independent
Classifier: Topic :: Software Development
Classifier: Topic :: Internet :: WWW/HTTP
Classifier: License :: OSI Approved :: MIT License
Classifier: Programming Language :: Python :: 3.6
